resulting/__init__.py
resulting/_option.py
resulting/_result.py
resulting/_traceback.py
resulting/_wrappers.py
resulting/py.typed
resulting-1.3.0.dist-info/LICENSE
resulting-1.3.0.dist-info/WHEEL
resulting-1.3.0.dist-info/METADATA
resulting-1.3.0.dist-info/RECORD
