Metadata-Version: 2.1
Name: resulting
Version: 1.3.0
Summary: Rust's Result and Option in python
Author-email: Ben Brady <benbradybusiness@gmail.com>
Requires-Python: >=3.10
Classifier: Development Status :: 4 - Beta
Classifier: Intended Audience :: Developers
Classifier: Natural Language :: English
Classifier: Operating System :: OS Independent
Classifier: License :: OSI Approved :: MIT License
Classifier: Programming Language :: Python
Classifier: Programming Language :: Python :: 3.10
Classifier: Programming Language :: Python :: 3.11
Classifier: Typing :: Typed
Requires-Dist: pytest ; extra == "dev"
Project-URL: Source, https://github.com/Ben-Brady/result
Provides-Extra: dev
